django_lock_tokens-0.1.4.dist-info/DESCRIPTION.rst
django_lock_tokens-0.1.4.dist-info/METADATA
django_lock_tokens-0.1.4.dist-info/RECORD
django_lock_tokens-0.1.4.dist-info/WHEEL
django_lock_tokens-0.1.4.dist-info/metadata.json
django_lock_tokens-0.1.4.dist-info/top_level.txt
lock_tokens/__init__.py
lock_tokens/admin.py
lock_tokens/apps.py
lock_tokens/decorators.py
lock_tokens/exceptions.py
lock_tokens/managers.py
lock_tokens/models.py
lock_tokens/sessions.py
lock_tokens/settings.py
lock_tokens/urls.py
lock_tokens/utils.py
lock_tokens/views.py
lock_tokens/management/__init__.py
lock_tokens/management/commands/__init__.py
lock_tokens/management/commands/remove_expired_locks.py
lock_tokens/migrations/0001_initial.py
lock_tokens/migrations/0002_locktoken_created.py
lock_tokens/migrations/__init__.py
lock_tokens/static/lock_tokens/js/lock_tokens.js
lock_tokens/templates/admin/lock_tokens_change_form.html
lock_tokens/templates/api/load_client.html
lock_tokens/templatetags/__init__.py
lock_tokens/templatetags/lock_tokens_tags.py
