Metadata-Version: 2.0
Name: django-lock-tokens
Version: 0.1.4
Summary: A Django application that provides a locking mechanism to prevent concurrency editing.
Home-page: https://github.com/rparent/django-lock-tokens
Author: Renaud Parent
Author-email: renaud.parent@gmail.com
License: MIT
Keywords: django-lock-tokens
Platform: UNKNOWN
Classifier: Development Status :: 4 - Beta
Classifier: Framework :: Django
Classifier: Framework :: Django :: 1.8
Classifier: Framework :: Django :: 1.9
Classifier: Framework :: Django :: 1.10
Classifier: Intended Audience :: Developers
Classifier: Topic :: Software Development :: Libraries :: Application Frameworks
Classifier: License :: OSI Approved :: MIT License
Classifier: Natural Language :: English
Classifier: Programming Language :: Python :: 2
Classifier: Programming Language :: Python :: 2.7
Classifier: Programming Language :: Python :: 3
Classifier: Programming Language :: Python :: 3.3
Classifier: Programming Language :: Python :: 3.4
Classifier: Programming Language :: Python :: 3.5
